Verilog Projects/debug_tb.v
`include "debug.v"
module tb_Processor;

    reg clk;
    reg [7:0] instruction;
    reg [7:0] dataIn;
    wire [7:0] dataOut;

    // Instantiate the Processor
    Processor uut (
        .clk(clk),
        .instruction(instruction),
        .dataIn(dataIn),
        .dataOut(dataOut)
    );

    // Clock generation
    always #5 clk = ~clk;

    initial begin
        // Initialize signals
        clk = 0;
        instruction = 8'b00000000;
        dataIn = 8'b00000000;

        // Test Load Operation
        #10 instruction = 8'b00000000; // LOAD instruction with address 0
        dataIn = 8'h10; // Data to load into memory
        #10; // Wait for load

        // Check data loaded into register
        #10 instruction = 8'b00000001; // Read data from register
        #10;

        // Test Store Operation
        #10 instruction = 8'b00010000; // STORE instruction with address 1
        dataIn = 8'h20; // Data to store in memory
        #10;

        // Check data stored in memory
        #10 instruction = 8'b00000001; // Read data from memory
        #10;

        // Test ALU Operations
        #10 instruction = 8'b00100000; // ADD instruction
        dataIn = 8'h05; // Value to add
        #10;

        // Check ALU output
        #10 instruction = 8'b00110000; // SUB instruction
        dataIn = 8'h03; // Value to subtract
        #10;

        // Test other ALU operations
        #10 $finish;
    end

    initial begin
        $monitor("Time: %0t | Instruction: %b | Data In: %h | Data Out: %h", 
                 $time, instruction, dataIn, dataOut);
    end

endmodule

Verilog Projects/debug.v
module ALU (
    input [7:0] A, B,
    input [2:0] ALU_Sel,
    output reg [7:0] ALU_Out,
    output reg Zero,
    output reg Carry
);
    always @(*) begin
        case (ALU_Sel)
            3'b000: {Carry, ALU_Out} = A + B; // ADD
            3'b001: {Carry, ALU_Out} = A - B; // SUB
            3'b010: ALU_Out = A & B; // AND
            3'b011: ALU_Out = A | B; // OR
            3'b100: ALU_Out = A ^ B; // XOR
            3'b101: ALU_Out = ~A;    // NOT
            default: ALU_Out = 8'b00000000;
        endcase
        Zero = (ALU_Out == 8'b00000000);
    end
endmodule
module PSW (
    input ZeroFlag,
    input CarryFlag,
    output reg [1:0] PSW
);
    always @(*) begin
        PSW = {CarryFlag, ZeroFlag};
    end
endmodule
module RegisterBank (
    input clk,
    input [2:0] regAddr,
    input [7:0] writeData,
    input writeEnable,
    output reg [7:0] readData
);
    reg [7:0] registers [7:0]; // 8 registers, 8-bit each

    always @(posedge clk) begin
        if (writeEnable) begin
            registers[regAddr] <= writeData;
        end
    end

    always @(*) begin
        readData = registers[regAddr];
    end
endmodule
module MemoryBank (
    input clk,
    input [7:0] addr,
    input [7:0] writeData,
    input memWrite,
    output reg [7:0] readData
);
    reg [7:0] memory [255:0]; // 256 bytes of memory

    always @(posedge clk) begin
        if (memWrite) begin
            memory[addr] <= writeData;
        end
    end

    always @(*) begin
        readData = memory[addr];
    end
endmodule
module InterruptController (
    input clk,
    input interrupt,
    output reg interruptSignal
);
    always @(posedge clk) begin
        interruptSignal = interrupt;
    end
endmodule
module ControlUnit (
    input [7:0] opcode,
    output reg [2:0] ALU_Sel,
    output reg memWrite,
    output reg load,
    output reg store
);

    always @(*) begin
        // Default values
        ALU_Sel = 3'b000;
        memWrite = 0;
        load = 0;
        store = 0;
        
        case (opcode[7:0])
            8'b00000000: begin // LOAD
                load = 1;
            end
            8'b00010000: begin // STORE
                store = 1;
            end
            8'b00100000: begin // ADD
                ALU_Sel = 3'b000;
            end
            8'b00110000: begin // SUB
                ALU_Sel = 3'b001;
            end
            // Add other ALU operations as needed
            default: begin
                // Handle unknown instructions
            end
        endcase
    end

endmodule

module Processor (
    input clk,
    input [7:0] instruction,
    input [7:0] dataIn,
    output reg [7:0] dataOut
);

    // Internal registers
    reg [7:0] regFile[0:7]; // Register file with 8 registers
    reg [7:0] mem[0:255];   // Memory with 256 locations
    reg [7:0] regData;      // Data read from registers
    reg [7:0] memAddr;      // Address for memory access
    reg [7:0] aluResult;    // Result from ALU

    // Control signals
    reg memWrite, loadEnable, storeEnable;
    wire [2:0] ALU_Sel;
    wire Zero, Carry;

    // ALU Instance
    ALU alu (
        .A(regData),
        .B(dataIn),
        .ALU_Sel(ALU_Sel),
        .ALU_Out(aluResult),
        .Zero(Zero),
        .Carry(Carry)
    );

    // Control Unit Instance
    ControlUnit controlUnit (
        .opcode(instruction),
        .ALU_Sel(ALU_Sel),
        .memWrite(memWrite),
        .load(loadEnable),
        .store(storeEnable)
    );

    // Update regData, regFile, and mem based on control signals
    always @(posedge clk) begin
        if (storeEnable) begin
            mem[memAddr] <= regData; // Store data from register to memory
        end
        if (loadEnable) begin
            regData <= mem[memAddr]; // Load data from memory to register
        end
        if (storeEnable) begin
            regFile[instruction[2:0]] <= aluResult; // Write ALU result to register
        end
        memAddr <= instruction[7:0]; // Update memory address
    end

    // DataOut assignment based on control signals
    always @(*) begin
        if (loadEnable) begin
            dataOut = regData; // Output data from register
        end else if (storeEnable) begin
            dataOut = aluResult; // Output data from ALU result
        end else begin
            dataOut = 8'bz; // High impedance if not loading or storing
        end
    end

endmodule

Verilog Projects/debug_tb.vcd
$date
	Fri Sep 06 19:52:37 2024
$end
$version
	Icarus Verilog
$end
$timescale
	1s
$end
$scope module InterruptController $end
$var wire 1 ! clk $end
$var wire 1 " interrupt $end
$var reg 1 # interruptSignal $end
$upscope $end
$scope module tb_Processor $end
$var wire 8 $ dataOut [7:0] $end
$var reg 1 % clk $end
$var reg 8 & dataIn [7:0] $end
$var reg 8 ' instruction [7:0] $end
$upscope $end
$enddefinitions $end
$comment Show the parameter values. $end
$dumpall
$end
#0
$dumpvars
b0 '
b0 &
0%
bx $
x#
z"
z!
$end
#5
1%
#10
0%
b10000 &
#15
1%
#20
0%
#25
1%
#30
0%
b101 &
b100000 '
#35
1%
#40
0%
#45
1%
#50
0%
b11 &
b110000 '
#55
1%
#60
0%
#65
1%
#70
bx0000 $
0%
b11110000 &
b1000000 '
#75
1%
#80
0%
#85
1%
#90
bx1111 $
0%
b1111 &
b1010000 '
#95
1%
#100
0%
#105
1%
#110
bx $
0%
b11111111 &
b1100000 '
#115
1%
#120
0%
#125
1%
#130
0%
b1110000 '
#135
1%
#140
0%
#145
1%
#150
0%
b10000 '
